sbermarket_api/__init__.py
sbermarket_api/api/__init__.py
sbermarket_api/api/client/__init__.py
sbermarket_api/api/client/get_stores.py
sbermarket_api/api/client/get_stores_store_id.py
sbermarket_api/api/store/__init__.py
sbermarket_api/api/store/get_stores_store_id_products.py
sbermarket_api/client.py
sbermarket_api/models/__init__.py
sbermarket_api/models/get_stores_shipping_method.py
sbermarket_api/models/search_products_response.py
sbermarket_api/models/search_products_response_facets_item.py
sbermarket_api/models/search_products_response_facets_item_options_item.py
sbermarket_api/models/search_products_response_meta.py
sbermarket_api/models/search_products_response_private_filters.py
sbermarket_api/models/search_products_response_products_item.py
sbermarket_api/models/search_products_response_root_categories.py
sbermarket_api/models/search_products_response_root_categories_options_item.py
sbermarket_api/models/search_products_response_sort_item.py
sbermarket_api/models/store.py
sbermarket_api/models/store_city.py
sbermarket_api/models/store_config.py
sbermarket_api/models/store_licenses_item.py
sbermarket_api/models/store_list_item.py
sbermarket_api/models/store_list_item_shipping_methods_item.py
sbermarket_api/models/store_location.py
sbermarket_api/models/store_operational_zone.py
sbermarket_api/models/store_payment_methods_stores_item.py
sbermarket_api/models/store_payment_methods_stores_item_payment_method.py
sbermarket_api/models/store_retailer.py
sbermarket_api/models/store_retailer_appearance.py
sbermarket_api/models/store_store_schedule.py
sbermarket_api/models/store_store_schedule_template.py
sbermarket_api/models/store_store_schedule_template_delivery_times_item.py
sbermarket_api/models/store_store_shipping_methods_item.py
sbermarket_api/models/store_store_shipping_methods_item_shipping_method.py
sbermarket_api/models/store_store_zones_item.py
sbermarket_api/models/store_tenants_item.py
sbermarket_api/py.typed
sbermarket_api/types.py
sbermarket_api-0.0.3.dist-info/LICENSE
sbermarket_api-0.0.3.dist-info/WHEEL
sbermarket_api-0.0.3.dist-info/METADATA
sbermarket_api-0.0.3.dist-info/RECORD
